{
    "version": "004.01",
    "description": "Free CJK font maintained by Japanese government agency. It covers a large set of characters.",
    "homepage": "https://moji.or.jp/ipafont/",
    "license": {
        "identifier": "Freeware",
        "url": "https://moji.or.jp/ipafont/license/"
    },
    "depends": "scoop-nerd-fonts-helper",
    "url": "https://moji.or.jp/wp-content/ipafont/IPAexfont/ipaexg00401.zip",
    "hash": "4ab6fee94bf6f94b3eeb31be2b73c559f738dc6b336d722d5301b1f3f592f850",
    "extract_dir": "ipaexg00401",
    "installer": {
        "script": [
            "try {",
            "    scoop-nerd-fonts-helper -Command install",
            "} catch {",
            "    abort($_, 1)",
            "}"
        ]
    },
    "uninstaller": {
        "script": [
            "try {",
            "    scoop-nerd-fonts-helper -Command uninstall",
            "} catch {",
            "    abort($_, 1)",
            "}"
        ]
    },
    "checkver": {
        "regex": "Ver\\.(\\d{3}\\.\\d{2}).*</span>"
    },
    "autoupdate": {
        "url": "https://moji.or.jp/wp-content/ipafont/IPAexfont/ipaexg$cleanVersion.zip",
        "extract_dir": "ipaexg$cleanVersion"
    }
}
